{
  "a_comp_cor_00": {
    "CumulativeVarianceExplained": 0.0401034544,
    "Mask": "combined",
    "Method": "aCompCor",
    "Retained": true,
    "SingularValue": 100.8241232237,
    "VarianceExplained": 0.0401034544
  },
  "a_comp_cor_01": {
    "CumulativeVarianceExplained": 0.0736912101,
    "Mask": "combined",
    "Method": "aCompCor",
    "Retained": true,
    "SingularValue": 92.2707509992,
    "VarianceExplained": 0.0335877557
  },
  "a_comp_cor_02": {
    "CumulativeVarianceExplained": 0.1055540672,
    "Mask": "combined",
    "Method": "aCompCor",
    "Retained": true,
    "SingularValue": 89.8702439241,
    "VarianceExplained": 0.0318628571
  },
  "a_comp_cor_03": {
    "CumulativeVarianceExplained": 0.1305193327,
    "Mask": "combined",
    "Method": "aCompCor",
    "Retained": true,
    "SingularValue": 79.5502698879,
    "VarianceExplained": 0.0249652655
  },
  "a_comp_cor_04": {
    "CumulativeVarianceExplained": 0.1522623995,
    "Mask": "combined",
    "Method": "aCompCor",
    "Retained": true,
    "SingularValue": 74.239316122,
    "VarianceExplained": 0.0217430668
  },
  "a_comp_cor_05": {
    "CumulativeVarianceExplained": 0.1711670603,
    "Mask": "combined",
    "Method": "aCompCor",
    "Retained": true,
    "SingularValue": 69.224209869,
    "VarianceExplained": 0.0189046608
  },
  "a_comp_cor_06": {
    "CumulativeVarianceExplained": 0.188566783,
    "Mask": "combined",
    "Method": "aCompCor",
    "Retained": true,
    "SingularValue": 66.4117196228,
    "VarianceExplained": 0.0173997227
  },
  "a_comp_cor_07": {
    "CumulativeVarianceExplained": 0.2031559443,
    "Mask": "combined",
    "Method": "aCompCor",
    "Retained": true,
    "SingularValue": 60.8119214308,
    "VarianceExplained": 0.0145891613
  },
  "a_comp_cor_08": {
    "CumulativeVarianceExplained": 0.2158364344,
    "Mask": "combined",
    "Method": "aCompCor",
    "Retained": true,
    "SingularValue": 56.6945851998,
    "VarianceExplained": 0.0126804901
  },
  "a_comp_cor_09": {
    "CumulativeVarianceExplained": 0.2279277782,
    "Mask": "combined",
    "Method": "aCompCor",
    "Retained": true,
    "SingularValue": 55.3618821504,
    "VarianceExplained": 0.0120913437
  },
  "a_comp_cor_10": {
    "CumulativeVarianceExplained": 0.2384492273,
    "Mask": "combined",
    "Method": "aCompCor",
    "Retained": true,
    "SingularValue": 51.6429857576,
    "VarianceExplained": 0.0105214492
  },
  "a_comp_cor_11": {
    "CumulativeVarianceExplained": 0.2486395218,
    "Mask": "combined",
    "Method": "aCompCor",
    "Retained": true,
    "SingularValue": 50.8237761487,
    "VarianceExplained": 0.0101902945
  },
  "a_comp_cor_12": {
    "CumulativeVarianceExplained": 0.2583047204,
    "Mask": "combined",
    "Method": "aCompCor",
    "Retained": true,
    "SingularValue": 49.4970086845,
    "VarianceExplained": 0.0096651986
  },
  "a_comp_cor_13": {
    "CumulativeVarianceExplained": 0.2675991731,
    "Mask": "combined",
    "Method": "aCompCor",
    "Retained": true,
    "SingularValue": 48.5384018711,
    "VarianceExplained": 0.0092944527
  },
  "a_comp_cor_14": {
    "CumulativeVarianceExplained": 0.2764611752,
    "Mask": "combined",
    "Method": "aCompCor",
    "Retained": true,
    "SingularValue": 47.3957596049,
    "VarianceExplained": 0.0088620021
  },
  "a_comp_cor_15": {
    "CumulativeVarianceExplained": 0.2852083641,
    "Mask": "combined",
    "Method": "aCompCor",
    "Retained": true,
    "SingularValue": 47.0877366564,
    "VarianceExplained": 0.0087471889
  },
  "a_comp_cor_16": {
    "CumulativeVarianceExplained": 0.2938416633,
    "Mask": "combined",
    "Method": "aCompCor",
    "Retained": true,
    "SingularValue": 46.7801874493,
    "VarianceExplained": 0.0086332992
  },
  "a_comp_cor_17": {
    "CumulativeVarianceExplained": 0.3024118696,
    "Mask": "combined",
    "Method": "aCompCor",
    "Retained": true,
    "SingularValue": 46.6089371297,
    "VarianceExplained": 0.0085702062
  },
  "a_comp_cor_18": {
    "CumulativeVarianceExplained": 0.3107618008,
    "Mask": "combined",
    "Method": "aCompCor",
    "Retained": true,
    "SingularValue": 46.0060567886,
    "VarianceExplained": 0.0083499312
  },
  "a_comp_cor_19": {
    "CumulativeVarianceExplained": 0.3189346751,
    "Mask": "combined",
    "Method": "aCompCor",
    "Retained": true,
    "SingularValue": 45.515673373,
    "VarianceExplained": 0.0081728743
  },
  "a_comp_cor_20": {
    "CumulativeVarianceExplained": 0.3270090457,
    "Mask": "combined",
    "Method": "aCompCor",
    "Retained": true,
    "SingularValue": 45.2405528317,
    "VarianceExplained": 0.0080743706
  },
  "a_comp_cor_21": {
    "CumulativeVarianceExplained": 0.335049586,
    "Mask": "combined",
    "Method": "aCompCor",
    "Retained": true,
    "SingularValue": 45.1456778842,
    "VarianceExplained": 0.0080405403
  },
  "a_comp_cor_22": {
    "CumulativeVarianceExplained": 0.342990972,
    "Mask": "combined",
    "Method": "aCompCor",
    "Retained": true,
    "SingularValue": 44.8664507922,
    "VarianceExplained": 0.007941386
  },
  "a_comp_cor_23": {
    "CumulativeVarianceExplained": 0.3508383581,
    "Mask": "combined",
    "Method": "aCompCor",
    "Retained": true,
    "SingularValue": 44.6001248529,
    "VarianceExplained": 0.0078473862
  },
  "a_comp_cor_24": {
    "CumulativeVarianceExplained": 0.3585991287,
    "Mask": "combined",
    "Method": "aCompCor",
    "Retained": true,
    "SingularValue": 44.3533048292,
    "VarianceExplained": 0.0077607706
  },
  "a_comp_cor_25": {
    "CumulativeVarianceExplained": 0.3663417819,
    "Mask": "combined",
    "Method": "aCompCor",
    "Retained": true,
    "SingularValue": 44.3015034974,
    "VarianceExplained": 0.0077426532
  },
  "a_comp_cor_26": {
    "CumulativeVarianceExplained": 0.373958741,
    "Mask": "combined",
    "Method": "aCompCor",
    "Retained": true,
    "SingularValue": 43.9404372067,
    "VarianceExplained": 0.0076169591
  },
  "a_comp_cor_27": {
    "CumulativeVarianceExplained": 0.3814953143,
    "Mask": "combined",
    "Method": "aCompCor",
    "Retained": true,
    "SingularValue": 43.7079590792,
    "VarianceExplained": 0.0075365734
  },
  "a_comp_cor_28": {
    "CumulativeVarianceExplained": 0.3889856156,
    "Mask": "combined",
    "Method": "aCompCor",
    "Retained": true,
    "SingularValue": 43.5735761281,
    "VarianceExplained": 0.0074903012
  },
  "a_comp_cor_29": {
    "CumulativeVarianceExplained": 0.396370374,
    "Mask": "combined",
    "Method": "aCompCor",
    "Retained": true,
    "SingularValue": 43.2654982785,
    "VarianceExplained": 0.0073847584
  },
  "a_comp_cor_30": {
    "CumulativeVarianceExplained": 0.4036958069,
    "Mask": "combined",
    "Method": "aCompCor",
    "Retained": true,
    "SingularValue": 43.0913609321,
    "VarianceExplained": 0.0073254329
  },
  "a_comp_cor_31": {
    "CumulativeVarianceExplained": 0.4108772906,
    "Mask": "combined",
    "Method": "aCompCor",
    "Retained": true,
    "SingularValue": 42.6658745183,
    "VarianceExplained": 0.0071814837
  },
  "a_comp_cor_32": {
    "CumulativeVarianceExplained": 0.4179859941,
    "Mask": "combined",
    "Method": "aCompCor",
    "Retained": true,
    "SingularValue": 42.4491269543,
    "VarianceExplained": 0.0071087035
  },
  "a_comp_cor_33": {
    "CumulativeVarianceExplained": 0.4250489025,
    "Mask": "combined",
    "Method": "aCompCor",
    "Retained": true,
    "SingularValue": 42.3121750055,
    "VarianceExplained": 0.0070629084
  },
  "a_comp_cor_34": {
    "CumulativeVarianceExplained": 0.4320667604,
    "Mask": "combined",
    "Method": "aCompCor",
    "Retained": true,
    "SingularValue": 42.1770154907,
    "VarianceExplained": 0.0070178578
  },
  "a_comp_cor_35": {
    "CumulativeVarianceExplained": 0.4390261431,
    "Mask": "combined",
    "Method": "aCompCor",
    "Retained": true,
    "SingularValue": 42.0009315696,
    "VarianceExplained": 0.0069593827
  },
  "a_comp_cor_36": {
    "CumulativeVarianceExplained": 0.4459482111,
    "Mask": "combined",
    "Method": "aCompCor",
    "Retained": true,
    "SingularValue": 41.8881801322,
    "VarianceExplained": 0.006922068
  },
  "a_comp_cor_37": {
    "CumulativeVarianceExplained": 0.4528374043,
    "Mask": "combined",
    "Method": "aCompCor",
    "Retained": true,
    "SingularValue": 41.7885926007,
    "VarianceExplained": 0.0068891932
  },
  "a_comp_cor_38": {
    "CumulativeVarianceExplained": 0.4596551203,
    "Mask": "combined",
    "Method": "aCompCor",
    "Retained": true,
    "SingularValue": 41.5712434895,
    "VarianceExplained": 0.006817716
  },
  "a_comp_cor_39": {
    "CumulativeVarianceExplained": 0.4664370277,
    "Mask": "combined",
    "Method": "aCompCor",
    "Retained": true,
    "SingularValue": 41.4619279912,
    "VarianceExplained": 0.0067819075
  },
  "a_comp_cor_40": {
    "CumulativeVarianceExplained": 0.4731670031,
    "Mask": "combined",
    "Method": "aCompCor",
    "Retained": true,
    "SingularValue": 41.3028766384,
    "VarianceExplained": 0.0067299754
  },
  "a_comp_cor_41": {
    "CumulativeVarianceExplained": 0.4798618598,
    "Mask": "combined",
    "Method": "aCompCor",
    "Retained": true,
    "SingularValue": 41.1949711936,
    "VarianceExplained": 0.0066948566
  },
  "a_comp_cor_42": {
    "CumulativeVarianceExplained": 0.4865467575,
    "Mask": "combined",
    "Method": "aCompCor",
    "Retained": true,
    "SingularValue": 41.1643200503,
    "VarianceExplained": 0.0066848977
  },
  "a_comp_cor_43": {
    "CumulativeVarianceExplained": 0.4931926623,
    "Mask": "combined",
    "Method": "aCompCor",
    "Retained": true,
    "SingularValue": 41.0440890323,
    "VarianceExplained": 0.0066459048
  },
  "a_comp_cor_44": {
    "CumulativeVarianceExplained": 0.4997189572,
    "Mask": "combined",
    "Method": "aCompCor",
    "Retained": true,
    "SingularValue": 40.6730656665,
    "VarianceExplained": 0.0065262948
  },
  "a_comp_cor_45": {
    "CumulativeVarianceExplained": 0.5061824056,
    "Mask": "combined",
    "Method": "aCompCor",
    "Retained": true,
    "SingularValue": 40.4767567126,
    "VarianceExplained": 0.0064634484
  },
  "aroma_motion_1": {
    "CSFFraction": 0.04,
    "EdgeFraction": 0.45,
    "HighFrequencyContent": 0.1,
    "MaximumRpCorrelation": 0.95,
    "Method": {
      "Name": "ICA-AROMA",
      "Version": "0.4.5"
    },
    "ModelVarianceExplained": 0.0665337569,
    "MotionNoise": true,
    "TotalVarianceExplained": 0.048319913
  },
  "aroma_motion_10": {
    "CSFFraction": 0.17,
    "EdgeFraction": 0.63,
    "HighFrequencyContent": 0.52,
    "MaximumRpCorrelation": 0.28,
    "Method": {
      "Name": "ICA-AROMA",
      "Version": "0.4.5"
    },
    "ModelVarianceExplained": 0.032661799,
    "MotionNoise": true,
    "TotalVarianceExplained": 0.0237205196
  },
  "aroma_motion_11": {
    "CSFFraction": 0.0,
    "EdgeFraction": 0.55,
    "HighFrequencyContent": 0.08,
    "MaximumRpCorrelation": 0.36,
    "Method": {
      "Name": "ICA-AROMA",
      "Version": "0.4.5"
    },
    "ModelVarianceExplained": 0.0319069422,
    "MotionNoise": false,
    "TotalVarianceExplained": 0.0231723074
  },
  "aroma_motion_12": {
    "CSFFraction": 0.03,
    "EdgeFraction": 0.62,
    "HighFrequencyContent": 0.86,
    "MaximumRpCorrelation": 0.64,
    "Method": {
      "Name": "ICA-AROMA",
      "Version": "0.4.5"
    },
    "ModelVarianceExplained": 0.0316840933,
    "MotionNoise": true,
    "TotalVarianceExplained": 0.0230104642
  },
  "aroma_motion_13": {
    "CSFFraction": 0.02,
    "EdgeFraction": 0.3,
    "HighFrequencyContent": 0.08,
    "MaximumRpCorrelation": 0.22,
    "Method": {
      "Name": "ICA-AROMA",
      "Version": "0.4.5"
    },
    "ModelVarianceExplained": 0.0315964859,
    "MotionNoise": false,
    "TotalVarianceExplained": 0.0229468397
  },
  "aroma_motion_14": {
    "CSFFraction": 0.05,
    "EdgeFraction": 0.61,
    "HighFrequencyContent": 0.69,
    "MaximumRpCorrelation": 0.51,
    "Method": {
      "Name": "ICA-AROMA",
      "Version": "0.4.5"
    },
    "ModelVarianceExplained": 0.0312859593,
    "MotionNoise": true,
    "TotalVarianceExplained": 0.0227213207
  },
  "aroma_motion_15": {
    "CSFFraction": 0.01,
    "EdgeFraction": 0.51,
    "HighFrequencyContent": 0.06,
    "MaximumRpCorrelation": 0.23,
    "Method": {
      "Name": "ICA-AROMA",
      "Version": "0.4.5"
    },
    "ModelVarianceExplained": 0.030642635,
    "MotionNoise": false,
    "TotalVarianceExplained": 0.0222541087
  },
  "aroma_motion_16": {
    "CSFFraction": 0.16,
    "EdgeFraction": 0.67,
    "HighFrequencyContent": 0.33,
    "MaximumRpCorrelation": 0.33,
    "Method": {
      "Name": "ICA-AROMA",
      "Version": "0.4.5"
    },
    "ModelVarianceExplained": 0.0298763767,
    "MotionNoise": true,
    "TotalVarianceExplained": 0.0216976162
  },
  "aroma_motion_17": {
    "CSFFraction": 0.0,
    "EdgeFraction": 0.36,
    "HighFrequencyContent": 0.11,
    "MaximumRpCorrelation": 0.19,
    "Method": {
      "Name": "ICA-AROMA",
      "Version": "0.4.5"
    },
    "ModelVarianceExplained": 0.0298093785,
    "MotionNoise": false,
    "TotalVarianceExplained": 0.021648959
  },
  "aroma_motion_18": {
    "CSFFraction": 0.01,
    "EdgeFraction": 0.34,
    "HighFrequencyContent": 0.12,
    "MaximumRpCorrelation": 0.23,
    "Method": {
      "Name": "ICA-AROMA",
      "Version": "0.4.5"
    },
    "ModelVarianceExplained": 0.0295306089,
    "MotionNoise": false,
    "TotalVarianceExplained": 0.0214465036
  },
  "aroma_motion_19": {
    "CSFFraction": 0.01,
    "EdgeFraction": 0.32,
    "HighFrequencyContent": 0.21,
    "MaximumRpCorrelation": 0.32,
    "Method": {
      "Name": "ICA-AROMA",
      "Version": "0.4.5"
    },
    "ModelVarianceExplained": 0.0287345345,
    "MotionNoise": false,
    "TotalVarianceExplained": 0.0208683572
  },
  "aroma_motion_2": {
    "CSFFraction": 0.0,
    "EdgeFraction": 0.42,
    "HighFrequencyContent": 0.08,
    "MaximumRpCorrelation": 0.32,
    "Method": {
      "Name": "ICA-AROMA",
      "Version": "0.4.5"
    },
    "ModelVarianceExplained": 0.0460401085,
    "MotionNoise": false,
    "TotalVarianceExplained": 0.0334364711
  },
  "aroma_motion_20": {
    "CSFFraction": 0.01,
    "EdgeFraction": 0.6,
    "HighFrequencyContent": 0.85,
    "MaximumRpCorrelation": 0.58,
    "Method": {
      "Name": "ICA-AROMA",
      "Version": "0.4.5"
    },
    "ModelVarianceExplained": 0.0277806007,
    "MotionNoise": true,
    "TotalVarianceExplained": 0.0201755661
  },
  "aroma_motion_21": {
    "CSFFraction": 0.03,
    "EdgeFraction": 0.54,
    "HighFrequencyContent": 0.57,
    "MaximumRpCorrelation": 0.39,
    "Method": {
      "Name": "ICA-AROMA",
      "Version": "0.4.5"
    },
    "ModelVarianceExplained": 0.0277061569,
    "MotionNoise": true,
    "TotalVarianceExplained": 0.0201215015
  },
  "aroma_motion_22": {
    "CSFFraction": 0.0,
    "EdgeFraction": 0.3,
    "HighFrequencyContent": 0.4,
    "MaximumRpCorrelation": 0.24,
    "Method": {
      "Name": "ICA-AROMA",
      "Version": "0.4.5"
    },
    "ModelVarianceExplained": 0.0264513266,
    "MotionNoise": true,
    "TotalVarianceExplained": 0.0192101853
  },
  "aroma_motion_23": {
    "CSFFraction": 0.02,
    "EdgeFraction": 0.75,
    "HighFrequencyContent": 0.21,
    "MaximumRpCorrelation": 0.6,
    "Method": {
      "Name": "ICA-AROMA",
      "Version": "0.4.5"
    },
    "ModelVarianceExplained": 0.0262875392,
    "MotionNoise": true,
    "TotalVarianceExplained": 0.0190912353
  },
  "aroma_motion_24": {
    "CSFFraction": 0.04,
    "EdgeFraction": 0.5,
    "HighFrequencyContent": 0.41,
    "MaximumRpCorrelation": 0.34,
    "Method": {
      "Name": "ICA-AROMA",
      "Version": "0.4.5"
    },
    "ModelVarianceExplained": 0.0261206569,
    "MotionNoise": true,
    "TotalVarianceExplained": 0.0189700376
  },
  "aroma_motion_25": {
    "CSFFraction": 0.04,
    "EdgeFraction": 0.44,
    "HighFrequencyContent": 0.54,
    "MaximumRpCorrelation": 0.33,
    "Method": {
      "Name": "ICA-AROMA",
      "Version": "0.4.5"
    },
    "ModelVarianceExplained": 0.0258648328,
    "MotionNoise": true,
    "TotalVarianceExplained": 0.0187842462
  },
  "aroma_motion_26": {
    "CSFFraction": 0.01,
    "EdgeFraction": 0.39,
    "HighFrequencyContent": 0.16,
    "MaximumRpCorrelation": 0.28,
    "Method": {
      "Name": "ICA-AROMA",
      "Version": "0.4.5"
    },
    "ModelVarianceExplained": 0.0258571875,
    "MotionNoise": false,
    "TotalVarianceExplained": 0.0187786938
  },
  "aroma_motion_27": {
    "CSFFraction": 0.07,
    "EdgeFraction": 0.46,
    "HighFrequencyContent": 0.52,
    "MaximumRpCorrelation": 0.42,
    "Method": {
      "Name": "ICA-AROMA",
      "Version": "0.4.5"
    },
    "ModelVarianceExplained": 0.0249579889,
    "MotionNoise": true,
    "TotalVarianceExplained": 0.0181256539
  },
  "aroma_motion_28": {
    "CSFFraction": 0.01,
    "EdgeFraction": 0.44,
    "HighFrequencyContent": 0.31,
    "MaximumRpCorrelation": 0.46,
    "Method": {
      "Name": "ICA-AROMA",
      "Version": "0.4.5"
    },
    "ModelVarianceExplained": 0.0238462189,
    "MotionNoise": false,
    "TotalVarianceExplained": 0.0173182348
  },
  "aroma_motion_29": {
    "CSFFraction": 0.02,
    "EdgeFraction": 0.71,
    "HighFrequencyContent": 0.84,
    "MaximumRpCorrelation": 0.62,
    "Method": {
      "Name": "ICA-AROMA",
      "Version": "0.4.5"
    },
    "ModelVarianceExplained": 0.0237073375,
    "MotionNoise": true,
    "TotalVarianceExplained": 0.0172173727
  },
  "aroma_motion_3": {
    "CSFFraction": 0.02,
    "EdgeFraction": 0.38,
    "HighFrequencyContent": 0.08,
    "MaximumRpCorrelation": 0.31,
    "Method": {
      "Name": "ICA-AROMA",
      "Version": "0.4.5"
    },
    "ModelVarianceExplained": 0.0431324438,
    "MotionNoise": false,
    "TotalVarianceExplained": 0.0313247895
  },
  "aroma_motion_30": {
    "CSFFraction": 0.05,
    "EdgeFraction": 0.42,
    "HighFrequencyContent": 0.22,
    "MaximumRpCorrelation": 0.26,
    "Method": {
      "Name": "ICA-AROMA",
      "Version": "0.4.5"
    },
    "ModelVarianceExplained": 0.0235106683,
    "MotionNoise": false,
    "TotalVarianceExplained": 0.0170745423
  },
  "aroma_motion_31": {
    "CSFFraction": 0.01,
    "EdgeFraction": 0.3,
    "HighFrequencyContent": 0.25,
    "MaximumRpCorrelation": 0.28,
    "Method": {
      "Name": "ICA-AROMA",
      "Version": "0.4.5"
    },
    "ModelVarianceExplained": 0.0232158682,
    "MotionNoise": false,
    "TotalVarianceExplained": 0.0168604448
  },
  "aroma_motion_32": {
    "CSFFraction": 0.04,
    "EdgeFraction": 0.64,
    "HighFrequencyContent": 0.45,
    "MaximumRpCorrelation": 0.24,
    "Method": {
      "Name": "ICA-AROMA",
      "Version": "0.4.5"
    },
    "ModelVarianceExplained": 0.0225071639,
    "MotionNoise": true,
    "TotalVarianceExplained": 0.0163457506
  },
  "aroma_motion_4": {
    "CSFFraction": 0.03,
    "EdgeFraction": 0.61,
    "HighFrequencyContent": 0.8,
    "MaximumRpCorrelation": 0.88,
    "Method": {
      "Name": "ICA-AROMA",
      "Version": "0.4.5"
    },
    "ModelVarianceExplained": 0.0379371531,
    "MotionNoise": true,
    "TotalVarianceExplained": 0.0275517275
  },
  "aroma_motion_5": {
    "CSFFraction": 0.03,
    "EdgeFraction": 0.7,
    "HighFrequencyContent": 0.42,
    "MaximumRpCorrelation": 0.67,
    "Method": {
      "Name": "ICA-AROMA",
      "Version": "0.4.5"
    },
    "ModelVarianceExplained": 0.0356386227,
    "MotionNoise": true,
    "TotalVarianceExplained": 0.0258824276
  },
  "aroma_motion_6": {
    "CSFFraction": 0.0,
    "EdgeFraction": 0.61,
    "HighFrequencyContent": 0.1,
    "MaximumRpCorrelation": 0.3,
    "Method": {
      "Name": "ICA-AROMA",
      "Version": "0.4.5"
    },
    "ModelVarianceExplained": 0.0355061788,
    "MotionNoise": false,
    "TotalVarianceExplained": 0.0257862407
  },
  "aroma_motion_7": {
    "CSFFraction": 0.01,
    "EdgeFraction": 0.39,
    "HighFrequencyContent": 0.1,
    "MaximumRpCorrelation": 0.46,
    "Method": {
      "Name": "ICA-AROMA",
      "Version": "0.4.5"
    },
    "ModelVarianceExplained": 0.0339675914,
    "MotionNoise": false,
    "TotalVarianceExplained": 0.0246688469
  },
  "aroma_motion_8": {
    "CSFFraction": 0.11,
    "EdgeFraction": 0.45,
    "HighFrequencyContent": 0.5,
    "MaximumRpCorrelation": 0.16,
    "Method": {
      "Name": "ICA-AROMA",
      "Version": "0.4.5"
    },
    "ModelVarianceExplained": 0.0329968141,
    "MotionNoise": true,
    "TotalVarianceExplained": 0.0239638232
  },
  "aroma_motion_9": {
    "CSFFraction": 0.01,
    "EdgeFraction": 0.52,
    "HighFrequencyContent": 0.08,
    "MaximumRpCorrelation": 0.28,
    "Method": {
      "Name": "ICA-AROMA",
      "Version": "0.4.5"
    },
    "ModelVarianceExplained": 0.0327049712,
    "MotionNoise": false,
    "TotalVarianceExplained": 0.0237518733
  },
  "c_comp_cor_00": {
    "CumulativeVarianceExplained": 0.1067813027,
    "Mask": "CSF",
    "Method": "aCompCor",
    "Retained": true,
    "SingularValue": 57.7272110441,
    "VarianceExplained": 0.1067813027
  },
  "c_comp_cor_01": {
    "CumulativeVarianceExplained": 0.1986789861,
    "Mask": "CSF",
    "Method": "aCompCor",
    "Retained": true,
    "SingularValue": 53.5531782873,
    "VarianceExplained": 0.0918976834
  },
  "c_comp_cor_02": {
    "CumulativeVarianceExplained": 0.2740546796,
    "Mask": "CSF",
    "Method": "aCompCor",
    "Retained": true,
    "SingularValue": 48.5007694765,
    "VarianceExplained": 0.0753756934
  },
  "c_comp_cor_03": {
    "CumulativeVarianceExplained": 0.3462599308,
    "Mask": "CSF",
    "Method": "aCompCor",
    "Retained": true,
    "SingularValue": 47.4697954706,
    "VarianceExplained": 0.0722052513
  },
  "c_comp_cor_04": {
    "CumulativeVarianceExplained": 0.3952131561,
    "Mask": "CSF",
    "Method": "aCompCor",
    "Retained": true,
    "SingularValue": 39.0862156624,
    "VarianceExplained": 0.0489532253
  },
  "c_comp_cor_05": {
    "CumulativeVarianceExplained": 0.4318371439,
    "Mask": "CSF",
    "Method": "aCompCor",
    "Retained": true,
    "SingularValue": 33.8077123043,
    "VarianceExplained": 0.0366239878
  },
  "c_comp_cor_06": {
    "CumulativeVarianceExplained": 0.4654166231,
    "Mask": "CSF",
    "Method": "aCompCor",
    "Retained": true,
    "SingularValue": 32.3720309486,
    "VarianceExplained": 0.0335794792
  },
  "c_comp_cor_07": {
    "CumulativeVarianceExplained": 0.4958191627,
    "Mask": "CSF",
    "Method": "aCompCor",
    "Retained": true,
    "SingularValue": 30.8026371476,
    "VarianceExplained": 0.0304025396
  },
  "c_comp_cor_08": {
    "CumulativeVarianceExplained": 0.5193883909,
    "Mask": "CSF",
    "Method": "aCompCor",
    "Retained": true,
    "SingularValue": 27.1209968728,
    "VarianceExplained": 0.0235692281
  },
  "csf": {
    "Method": "Mean"
  },
  "csf_wm": {
    "Method": "Mean"
  },
  "global_signal": {
    "Method": "Mean"
  },
  "t_comp_cor_00": {
    "CumulativeVarianceExplained": 0.1453139766,
    "Method": "tCompCor",
    "Retained": true,
    "SingularValue": 131.6042637506,
    "VarianceExplained": 0.1453139766
  },
  "t_comp_cor_01": {
    "CumulativeVarianceExplained": 0.2547645569,
    "Method": "tCompCor",
    "Retained": true,
    "SingularValue": 114.2155671069,
    "VarianceExplained": 0.1094505803
  },
  "t_comp_cor_02": {
    "CumulativeVarianceExplained": 0.3552998078,
    "Method": "tCompCor",
    "Retained": true,
    "SingularValue": 109.4650422709,
    "VarianceExplained": 0.1005352509
  },
  "t_comp_cor_03": {
    "CumulativeVarianceExplained": 0.4457013943,
    "Method": "tCompCor",
    "Retained": true,
    "SingularValue": 103.8016584807,
    "VarianceExplained": 0.0904015866
  },
  "t_comp_cor_04": {
    "CumulativeVarianceExplained": 0.5323713963,
    "Method": "tCompCor",
    "Retained": true,
    "SingularValue": 101.6367265699,
    "VarianceExplained": 0.0866700019
  },
  "tcompcor": {
    "Method": "Mean"
  },
  "w_comp_cor_00": {
    "CumulativeVarianceExplained": 0.0298759106,
    "Mask": "WM",
    "Method": "aCompCor",
    "Retained": true,
    "SingularValue": 69.5371564704,
    "VarianceExplained": 0.0298759106
  },
  "w_comp_cor_01": {
    "CumulativeVarianceExplained": 0.0552314243,
    "Mask": "WM",
    "Method": "aCompCor",
    "Retained": true,
    "SingularValue": 64.0608296665,
    "VarianceExplained": 0.0253555137
  },
  "w_comp_cor_02": {
    "CumulativeVarianceExplained": 0.0774401592,
    "Mask": "WM",
    "Method": "aCompCor",
    "Retained": true,
    "SingularValue": 59.9540135923,
    "VarianceExplained": 0.0222087349
  },
  "w_comp_cor_03": {
    "CumulativeVarianceExplained": 0.097406352,
    "Mask": "WM",
    "Method": "aCompCor",
    "Retained": true,
    "SingularValue": 56.8465328204,
    "VarianceExplained": 0.0199661927
  },
  "w_comp_cor_04": {
    "CumulativeVarianceExplained": 0.1154072601,
    "Mask": "WM",
    "Method": "aCompCor",
    "Retained": true,
    "SingularValue": 53.9763557387,
    "VarianceExplained": 0.0180009081
  },
  "w_comp_cor_05": {
    "CumulativeVarianceExplained": 0.1295321609,
    "Mask": "WM",
    "Method": "aCompCor",
    "Retained": true,
    "SingularValue": 47.8133369789,
    "VarianceExplained": 0.0141249008
  },
  "w_comp_cor_06": {
    "CumulativeVarianceExplained": 0.1425528351,
    "Mask": "WM",
    "Method": "aCompCor",
    "Retained": true,
    "SingularValue": 45.9063843548,
    "VarianceExplained": 0.0130206742
  },
  "w_comp_cor_07": {
    "CumulativeVarianceExplained": 0.1552516053,
    "Mask": "WM",
    "Method": "aCompCor",
    "Retained": true,
    "SingularValue": 45.3353720707,
    "VarianceExplained": 0.0126987702
  },
  "w_comp_cor_08": {
    "CumulativeVarianceExplained": 0.1668655291,
    "Mask": "WM",
    "Method": "aCompCor",
    "Retained": true,
    "SingularValue": 43.3556635078,
    "VarianceExplained": 0.0116139237
  },
  "w_comp_cor_09": {
    "CumulativeVarianceExplained": 0.1782071611,
    "Mask": "WM",
    "Method": "aCompCor",
    "Retained": true,
    "SingularValue": 42.8444061503,
    "VarianceExplained": 0.011341632
  },
  "w_comp_cor_10": {
    "CumulativeVarianceExplained": 0.1889934604,
    "Mask": "WM",
    "Method": "aCompCor",
    "Retained": true,
    "SingularValue": 41.7823234159,
    "VarianceExplained": 0.0107862994
  },
  "w_comp_cor_11": {
    "CumulativeVarianceExplained": 0.1995860506,
    "Mask": "WM",
    "Method": "aCompCor",
    "Retained": true,
    "SingularValue": 41.4054430743,
    "VarianceExplained": 0.0105925902
  },
  "w_comp_cor_12": {
    "CumulativeVarianceExplained": 0.2098733047,
    "Mask": "WM",
    "Method": "aCompCor",
    "Retained": true,
    "SingularValue": 40.8043145239,
    "VarianceExplained": 0.0102872541
  },
  "w_comp_cor_13": {
    "CumulativeVarianceExplained": 0.219886148,
    "Mask": "WM",
    "Method": "aCompCor",
    "Retained": true,
    "SingularValue": 40.2564116814,
    "VarianceExplained": 0.0100128433
  },
  "w_comp_cor_14": {
    "CumulativeVarianceExplained": 0.2298230287,
    "Mask": "WM",
    "Method": "aCompCor",
    "Retained": true,
    "SingularValue": 40.1034180144,
    "VarianceExplained": 0.0099368807
  },
  "w_comp_cor_15": {
    "CumulativeVarianceExplained": 0.2395017694,
    "Mask": "WM",
    "Method": "aCompCor",
    "Retained": true,
    "SingularValue": 39.57908785,
    "VarianceExplained": 0.0096787408
  },
  "w_comp_cor_16": {
    "CumulativeVarianceExplained": 0.2491444309,
    "Mask": "WM",
    "Method": "aCompCor",
    "Retained": true,
    "SingularValue": 39.5052496928,
    "VarianceExplained": 0.0096426614
  },
  "w_comp_cor_17": {
    "CumulativeVarianceExplained": 0.258728936,
    "Mask": "WM",
    "Method": "aCompCor",
    "Retained": true,
    "SingularValue": 39.3859386234,
    "VarianceExplained": 0.0095845052
  },
  "w_comp_cor_18": {
    "CumulativeVarianceExplained": 0.2681924834,
    "Mask": "WM",
    "Method": "aCompCor",
    "Retained": true,
    "SingularValue": 39.1366214544,
    "VarianceExplained": 0.0094635474
  },
  "w_comp_cor_19": {
    "CumulativeVarianceExplained": 0.2775084897,
    "Mask": "WM",
    "Method": "aCompCor",
    "Retained": true,
    "SingularValue": 38.8303440389,
    "VarianceExplained": 0.0093160063
  },
  "w_comp_cor_20": {
    "CumulativeVarianceExplained": 0.2866898064,
    "Mask": "WM",
    "Method": "aCompCor",
    "Retained": true,
    "SingularValue": 38.548620173,
    "VarianceExplained": 0.0091813168
  },
  "w_comp_cor_21": {
    "CumulativeVarianceExplained": 0.2958323219,
    "Mask": "WM",
    "Method": "aCompCor",
    "Retained": true,
    "SingularValue": 38.4670785307,
    "VarianceExplained": 0.0091425155
  },
  "w_comp_cor_22": {
    "CumulativeVarianceExplained": 0.3048640491,
    "Mask": "WM",
    "Method": "aCompCor",
    "Retained": true,
    "SingularValue": 38.2332976548,
    "VarianceExplained": 0.0090317272
  },
  "w_comp_cor_23": {
    "CumulativeVarianceExplained": 0.3137268396,
    "Mask": "WM",
    "Method": "aCompCor",
    "Retained": true,
    "SingularValue": 37.8740365116,
    "VarianceExplained": 0.0088627905
  },
  "w_comp_cor_24": {
    "CumulativeVarianceExplained": 0.32255585,
    "Mask": "WM",
    "Method": "aCompCor",
    "Retained": true,
    "SingularValue": 37.8017899795,
    "VarianceExplained": 0.0088290104
  },
  "w_comp_cor_25": {
    "CumulativeVarianceExplained": 0.3313257732,
    "Mask": "WM",
    "Method": "aCompCor",
    "Retained": true,
    "SingularValue": 37.6750856569,
    "VarianceExplained": 0.0087699233
  },
  "w_comp_cor_26": {
    "CumulativeVarianceExplained": 0.3399151534,
    "Mask": "WM",
    "Method": "aCompCor",
    "Retained": true,
    "SingularValue": 37.2852674888,
    "VarianceExplained": 0.0085893801
  },
  "w_comp_cor_27": {
    "CumulativeVarianceExplained": 0.3484249436,
    "Mask": "WM",
    "Method": "aCompCor",
    "Retained": true,
    "SingularValue": 37.1121213074,
    "VarianceExplained": 0.0085097902
  },
  "w_comp_cor_28": {
    "CumulativeVarianceExplained": 0.3568750259,
    "Mask": "WM",
    "Method": "aCompCor",
    "Retained": true,
    "SingularValue": 36.9816958869,
    "VarianceExplained": 0.0084500824
  },
  "w_comp_cor_29": {
    "CumulativeVarianceExplained": 0.365180625,
    "Mask": "WM",
    "Method": "aCompCor",
    "Retained": true,
    "SingularValue": 36.664167813,
    "VarianceExplained": 0.008305599
  },
  "w_comp_cor_30": {
    "CumulativeVarianceExplained": 0.3734402825,
    "Mask": "WM",
    "Method": "aCompCor",
    "Retained": true,
    "SingularValue": 36.5626254091,
    "VarianceExplained": 0.0082596576
  },
  "w_comp_cor_31": {
    "CumulativeVarianceExplained": 0.3816736448,
    "Mask": "WM",
    "Method": "aCompCor",
    "Retained": true,
    "SingularValue": 36.5043790292,
    "VarianceExplained": 0.0082333623
  },
  "w_comp_cor_32": {
    "CumulativeVarianceExplained": 0.389793972,
    "Mask": "WM",
    "Method": "aCompCor",
    "Retained": true,
    "SingularValue": 36.2529303438,
    "VarianceExplained": 0.0081203272
  },
  "w_comp_cor_33": {
    "CumulativeVarianceExplained": 0.3978495342,
    "Mask": "WM",
    "Method": "aCompCor",
    "Retained": true,
    "SingularValue": 36.108070257,
    "VarianceExplained": 0.0080555622
  },
  "w_comp_cor_34": {
    "CumulativeVarianceExplained": 0.4058493244,
    "Mask": "WM",
    "Method": "aCompCor",
    "Retained": true,
    "SingularValue": 35.9828575604,
    "VarianceExplained": 0.0079997902
  },
  "w_comp_cor_35": {
    "CumulativeVarianceExplained": 0.4136947639,
    "Mask": "WM",
    "Method": "aCompCor",
    "Retained": true,
    "SingularValue": 35.6340341087,
    "VarianceExplained": 0.0078454395
  },
  "w_comp_cor_36": {
    "CumulativeVarianceExplained": 0.4214737757,
    "Mask": "WM",
    "Method": "aCompCor",
    "Retained": true,
    "SingularValue": 35.4828557646,
    "VarianceExplained": 0.0077790118
  },
  "w_comp_cor_37": {
    "CumulativeVarianceExplained": 0.4292376796,
    "Mask": "WM",
    "Method": "aCompCor",
    "Retained": true,
    "SingularValue": 35.4483828969,
    "VarianceExplained": 0.0077639039
  },
  "w_comp_cor_38": {
    "CumulativeVarianceExplained": 0.43694908,
    "Mask": "WM",
    "Method": "aCompCor",
    "Retained": true,
    "SingularValue": 35.3283194825,
    "VarianceExplained": 0.0077114004
  },
  "w_comp_cor_39": {
    "CumulativeVarianceExplained": 0.4445758571,
    "Mask": "WM",
    "Method": "aCompCor",
    "Retained": true,
    "SingularValue": 35.1339418842,
    "VarianceExplained": 0.0076267771
  },
  "w_comp_cor_40": {
    "CumulativeVarianceExplained": 0.4521689061,
    "Mask": "WM",
    "Method": "aCompCor",
    "Retained": true,
    "SingularValue": 35.0561688775,
    "VarianceExplained": 0.007593049
  },
  "w_comp_cor_41": {
    "CumulativeVarianceExplained": 0.4597098931,
    "Mask": "WM",
    "Method": "aCompCor",
    "Retained": true,
    "SingularValue": 34.9357803648,
    "VarianceExplained": 0.007540987
  },
  "w_comp_cor_42": {
    "CumulativeVarianceExplained": 0.4671335594,
    "Mask": "WM",
    "Method": "aCompCor",
    "Retained": true,
    "SingularValue": 34.6629541017,
    "VarianceExplained": 0.0074236663
  },
  "w_comp_cor_43": {
    "CumulativeVarianceExplained": 0.4744924526,
    "Mask": "WM",
    "Method": "aCompCor",
    "Retained": true,
    "SingularValue": 34.5114021123,
    "VarianceExplained": 0.0073588933
  },
  "w_comp_cor_44": {
    "CumulativeVarianceExplained": 0.4817793556,
    "Mask": "WM",
    "Method": "aCompCor",
    "Retained": true,
    "SingularValue": 34.3421788477,
    "VarianceExplained": 0.007286903
  },
  "w_comp_cor_45": {
    "CumulativeVarianceExplained": 0.4890133128,
    "Mask": "WM",
    "Method": "aCompCor",
    "Retained": true,
    "SingularValue": 34.2171882866,
    "VarianceExplained": 0.0072339572
  },
  "w_comp_cor_46": {
    "CumulativeVarianceExplained": 0.4961167249,
    "Mask": "WM",
    "Method": "aCompCor",
    "Retained": true,
    "SingularValue": 33.9070383226,
    "VarianceExplained": 0.0071034121
  },
  "w_comp_cor_47": {
    "CumulativeVarianceExplained": 0.5031945751,
    "Mask": "WM",
    "Method": "aCompCor",
    "Retained": true,
    "SingularValue": 33.8459754208,
    "VarianceExplained": 0.0070778502
  },
  "white_matter": {
    "Method": "Mean"
  }
}